LICENSE.txt
pyproject.toml
setup.py
curling/__init__.py
curling/constants.py
curling/curling.py
curling/enums.py
curling/stone.c
curling/utils.py
curling.egg-info/PKG-INFO
curling.egg-info/SOURCES.txt
curling.egg-info/dependency_links.txt
curling.egg-info/not-zip-safe
curling.egg-info/requires.txt
curling.egg-info/top_level.txt
tests/test_display.py
tests/test_gameplay.py
tests/test_physics.py